myio/__init__.py
myio/comms_thread.py
myio/const.py
myio-0.0.6.dist-info/METADATA
myio-0.0.6.dist-info/WHEEL
myio-0.0.6.dist-info/top_level.txt
myio-0.0.6.dist-info/RECORD
