Metadata-Version: 2.1
Name: myio
Version: 0.0.6
Summary: This package contains myIO-server communication
Home-page: https://github.com/SmarthomeNinja/home-assistant
Author: Peter Szabo
Author-email: info@smarthome.ninja
License: UNKNOWN
Platform: UNKNOWN
Classifier: Programming Language :: Python :: 3
Classifier: License :: OSI Approved :: MIT License
Classifier: Operating System :: OS Independent
Requires-Python: >=3.6
